quran_transcript/__init__.py
quran_transcript/alphabet.py
quran_transcript/tasmeea.py
quran_transcript/utils.py
quran_transcript/phonetics/__init__.py
quran_transcript/phonetics/conv_base_operation.py
quran_transcript/phonetics/generate_moshaf_docs.py
quran_transcript/phonetics/moshaf_attributes.py
quran_transcript/phonetics/operations.py
quran_transcript/phonetics/phonetizer.py
quran_transcript/phonetics/sifa.py
quran_transcript/quran-script/begin_with_hamzat_wasl.json
quran_transcript/quran-script/quran-alphabet.json
quran_transcript/quran-script/quran-simple-imlaey-without-puase-sajda-hizb-marks-and-tatweel.xml
quran_transcript/quran-script/quran-uthmani-imlaey-map.json
quran_transcript/quran-script/quran-uthmani-imlaey.json
quran_transcript/quran-script/quran-uthmani-imlaey.xml
quran_transcript/quran-script/quran-uthmani-without-pause-sajda-hizb-marks.xml
quran_transcript/quran-script/quranic-corpus-morphology-0.4.txt
quran_transcript-0.1.2.dist-info/licenses/LICENSE
quran_transcript-0.1.2.dist-info/METADATA
quran_transcript-0.1.2.dist-info/WHEEL
quran_transcript-0.1.2.dist-info/entry_points.txt
quran_transcript-0.1.2.dist-info/top_level.txt
quran_transcript-0.1.2.dist-info/RECORD
