Metadata-Version: 2.4
Name: quran-transcript
Version: 0.1.2
Summary: Quran Phonetic Script with addional quarnic utils
Author-email: Abdullah <abdullahamlyossef@gmail.com>
License-Expression: MIT
Project-URL: Homepage, https://github.com/obadx/quran-transcript
Project-URL: Issues, https://github.com/obadx/quran-transcript/issues
Classifier: Programming Language :: Python :: 3.10
Classifier: Programming Language :: Python :: 3.11
Classifier: Programming Language :: Python :: 3.12
Classifier: Programming Language :: Python :: 3.13
Classifier: Programming Language :: Python :: 3.14
Classifier: Operating System :: OS Independent
Requires-Python: >=3.10
License-File: LICENSE
Requires-Dist: levenshtein>=0.27.1
Requires-Dist: pydantic>=2.12.5
Requires-Dist: xmltodict
Requires-Dist: typing_extensions>=4.0.0; python_version < "3.11"
Provides-Extra: test
Requires-Dist: pytest; extra == "test"
Dynamic: license-file
